pyufw/__init__.py
pyufw/pyufw.py
pyufw-0.0.3.dist-info/LICENSE
pyufw-0.0.3.dist-info/METADATA
pyufw-0.0.3.dist-info/WHEEL
pyufw-0.0.3.dist-info/top_level.txt
pyufw-0.0.3.dist-info/RECORD
